{
  "cert": "1527",
  "name": "Diamond Bank",
  "peer_group": "community",
  "peer_group_bank_count": 4075,
  "assets": 836272,
  "deposits": 746885,
  "uninsured_pct": null,
  "state": "AR",
  "charter": "SM",
  "repdte": "2024-12-31",
  "run_risk_score": 56.41379327961581,
  "stickiness_score": 43.58620672038419,
  "run_risk": 76.51063829787233,
  "alm_mismatch": 71.36131789346007,
  "treasury_buffer": 29.058479532163744,
  "deposit_competition": 11.148936170212766,
  "deposit_competition_resilience": 88.85106382978724,
  "deposit_competition_score": 34.511206616696995,
  "funding_fragility": 73.33708657010021,
  "run_risk_components": [
    {
      "key": "uninsured_share",
      "label": "Uninsured deposits",
      "weight": 0.2,
      "percentile": 50.0,
      "contribution": 12.82051282051282
    },
    {
      "key": "brokered_share",
      "label": "Brokered deposits",
      "weight": 0.17,
      "percentile": 57.21293199554069,
      "contribution": 12.469485178515278
    },
    {
      "key": "list_service_share",
      "label": "List-service deposits",
      "weight": 0.08,
      "percentile": 83.01003344481606,
      "contribution": 8.513849584083697
    },
    {
      "key": "large_account_share",
      "label": "Large-account concentration",
      "weight": 0.1,
      "percentile": 50.0,
      "contribution": 6.41025641025641
    },
    {
      "key": "time_deposit_share",
      "label": "Time-deposit share",
      "weight": 0.05,
      "percentile": 85.30657748049052,
      "contribution": 5.468370351313495
    },
    {
      "key": "domestic_deposit_cost",
      "label": "Domestic deposit cost",
      "weight": 0.08,
      "percentile": 82.28469433288711,
      "contribution": 8.439455829014063
    },
    {
      "key": "dep_growth_vol_4q",
      "label": "Deposit-growth volatility",
      "weight": 0.05,
      "percentile": 9.697508896797153,
      "contribution": 0.6216351856921252
    },
    {
      "key": "dep_drawdown_4q",
      "label": "Deposit drawdown",
      "weight": 0.05,
      "percentile": 26.055555555555554,
      "contribution": 1.6702279202279202
    }
  ],
  "deposit_competition_components": [
    {
      "key": "outside_option_premium_pos_bp",
      "label": "Outside-option premium",
      "weight": 0.35,
      "percentile": 17.737617135207497,
      "contribution": 6.208165997322624
    },
    {
      "key": "pass_through_gap_bp",
      "label": "Pass-through gap",
      "weight": 0.2,
      "percentile": 48.46016514170944,
      "contribution": 9.69203302834189
    },
    {
      "key": "rate_sensitive_deposit_exposure",
      "label": "Rate-sensitive deposit exposure",
      "weight": 0.1,
      "percentile": 55.35277097707545,
      "contribution": 5.535277097707546
    },
    {
      "key": "premium_x_rate_sensitive_exposure",
      "label": "Premium \u00d7 rate-sensitive exposure",
      "weight": 0.2,
      "percentile": 35.54216867469879,
      "contribution": 7.108433734939759
    },
    {
      "key": "premium_x_dep_drawdown_4q",
      "label": "Premium \u00d7 deposit drawdown",
      "weight": 0.1,
      "percentile": 26.17135207496653,
      "contribution": 2.6171352074966534
    },
    {
      "key": "premium_x_short_fhlb_share",
      "label": "Premium \u00d7 short FHLB share",
      "weight": 0.05,
      "percentile": 67.00323101777059,
      "contribution": 3.3501615508885294
    }
  ],
  "alm_components": [
    {
      "key": "long_term_assets_to_stable_funding_baseline",
      "label": "Long-term assets / stable funding",
      "weight": 0.3,
      "contribution": 22.555366269165248
    },
    {
      "key": "volatile_to_liquid_lower",
      "label": "Volatile funding / liquid assets",
      "weight": 0.3,
      "contribution": 15.0
    },
    {
      "key": "security_vs_deposit_gap_baseline",
      "label": "Securities / deposit gap",
      "weight": 0.2,
      "contribution": 18.547287281351913
    },
    {
      "key": "loans_to_core_deposits",
      "label": "Loans / core deposits",
      "weight": 0.1,
      "contribution": 6.726241134751773
    },
    {
      "key": "short_fhlb_share",
      "label": "Short FHLB funding share",
      "weight": 0.1,
      "contribution": 8.532423208191126
    }
  ],
  "treasury_buffer_components": [
    {
      "key": "treasury_to_uninsured_after_100bp",
      "label": "Treasuries / uninsured after 100 bp shock",
      "weight": 0.35,
      "contribution": 17.5
    },
    {
      "key": "treasury_agency_to_runnable",
      "label": "Treasury-agency / runnable funding",
      "weight": 0.35,
      "contribution": 9.773391812865498
    },
    {
      "key": "hqla_narrow_lower_to_runnable",
      "label": "Narrow HQLA / runnable funding",
      "weight": 0.3,
      "contribution": 1.7850877192982457
    }
  ],
  "composite_components": [
    {
      "key": "run_risk_index",
      "label": "Run Risk Index",
      "weight": 0.4,
      "score": 76.51063829787233,
      "contribution": 30.604255319148933
    },
    {
      "key": "alm_mismatch_index",
      "label": "ALM Mismatch Index",
      "weight": 0.4,
      "score": 71.36131789346007,
      "contribution": 28.544527157384028
    },
    {
      "key": "inverse_treasury_buffer_index",
      "label": "Inverse Treasury Buffer",
      "weight": 0.2,
      "score": 70.94152046783626,
      "contribution": 14.188304093567252
    }
  ],
  "supervised_outflow_score": 0.18095250893911025,
  "treasury_yield_date": "2024-12-31",
  "has_treasury_yield_history": 1,
  "yc_2yr": 4.25,
  "yc_10yr": 4.58,
  "yc_10y_3m_slope_bp": 20.999999999999996,
  "yc_10y_2y_slope_bp": 33.00000000000001,
  "yc_10yr_qoq_change_bp": 77.0,
  "has_ffiec_features": 1,
  "has_sod_features": 0,
  "index_version": "v1_ffiec_hybrid",
  "failed": false,
  "fail_date": null
}