{
  "cert": "2157",
  "name": "First State Bank of Randolph County",
  "peer_group": "community",
  "peer_group_bank_count": 4075,
  "assets": 88991,
  "deposits": 88981,
  "uninsured_pct": null,
  "state": "GA",
  "charter": "NM",
  "repdte": "2024-12-31",
  "run_risk_score": 43.6874899355801,
  "stickiness_score": 56.3125100644199,
  "run_risk": 35.716312056737586,
  "alm_mismatch": 51.498638426230755,
  "treasury_buffer": 67.8406432748538,
  "deposit_competition": 66.04255319148936,
  "deposit_competition_resilience": 33.95744680851064,
  "deposit_competition_score": 53.51945513857474,
  "funding_fragility": 41.31785153821657,
  "run_risk_components": [
    {
      "key": "uninsured_share",
      "label": "Uninsured deposits",
      "weight": 0.2,
      "percentile": 50.0,
      "contribution": 12.82051282051282
    },
    {
      "key": "brokered_share",
      "label": "Brokered deposits",
      "weight": 0.17,
      "percentile": 25.908584169453736,
      "contribution": 5.646742703598892
    },
    {
      "key": "list_service_share",
      "label": "List-service deposits",
      "weight": 0.08,
      "percentile": 39.40914158305463,
      "contribution": 4.0419632392876546
    },
    {
      "key": "large_account_share",
      "label": "Large-account concentration",
      "weight": 0.1,
      "percentile": 50.0,
      "contribution": 6.41025641025641
    },
    {
      "key": "time_deposit_share",
      "label": "Time-deposit share",
      "weight": 0.05,
      "percentile": 62.474916387959865,
      "contribution": 4.00480233256153
    },
    {
      "key": "domestic_deposit_cost",
      "label": "Domestic deposit cost",
      "weight": 0.08,
      "percentile": 36.74698795180723,
      "contribution": 3.768921841210998
    },
    {
      "key": "dep_growth_vol_4q",
      "label": "Deposit-growth volatility",
      "weight": 0.05,
      "percentile": 49.79982206405694,
      "contribution": 3.192296286157496
    },
    {
      "key": "dep_drawdown_4q",
      "label": "Deposit drawdown",
      "weight": 0.05,
      "percentile": 59.31111111111112,
      "contribution": 3.8019943019943025
    }
  ],
  "deposit_competition_components": [
    {
      "key": "outside_option_premium_pos_bp",
      "label": "Outside-option premium",
      "weight": 0.35,
      "percentile": 63.27532351628737,
      "contribution": 22.14636323070058
    },
    {
      "key": "pass_through_gap_bp",
      "label": "Pass-through gap",
      "weight": 0.2,
      "percentile": 48.46016514170944,
      "contribution": 9.69203302834189
    },
    {
      "key": "rate_sensitive_deposit_exposure",
      "label": "Rate-sensitive deposit exposure",
      "weight": 0.1,
      "percentile": 36.81281994213221,
      "contribution": 3.681281994213221
    },
    {
      "key": "premium_x_rate_sensitive_exposure",
      "label": "Premium \u00d7 rate-sensitive exposure",
      "weight": 0.2,
      "percentile": 46.787148594377506,
      "contribution": 9.357429718875501
    },
    {
      "key": "premium_x_dep_drawdown_4q",
      "label": "Premium \u00d7 deposit drawdown",
      "weight": 0.1,
      "percentile": 61.423471664435525,
      "contribution": 6.142347166443553
    },
    {
      "key": "premium_x_short_fhlb_share",
      "label": "Premium \u00d7 short FHLB share",
      "weight": 0.05,
      "percentile": 50.0,
      "contribution": 2.5
    }
  ],
  "alm_components": [
    {
      "key": "long_term_assets_to_stable_funding_baseline",
      "label": "Long-term assets / stable funding",
      "weight": 0.3,
      "contribution": 22.061328790459964
    },
    {
      "key": "volatile_to_liquid_lower",
      "label": "Volatile funding / liquid assets",
      "weight": 0.3,
      "contribution": 11.807383627608347
    },
    {
      "key": "security_vs_deposit_gap_baseline",
      "label": "Securities / deposit gap",
      "weight": 0.2,
      "contribution": 12.04269196560925
    },
    {
      "key": "loans_to_core_deposits",
      "label": "Loans / core deposits",
      "weight": 0.1,
      "contribution": 0.5872340425531916
    },
    {
      "key": "short_fhlb_share",
      "label": "Short FHLB funding share",
      "weight": 0.1,
      "contribution": 5.0
    }
  ],
  "treasury_buffer_components": [
    {
      "key": "treasury_to_uninsured_after_100bp",
      "label": "Treasuries / uninsured after 100 bp shock",
      "weight": 0.35,
      "contribution": 17.5
    },
    {
      "key": "treasury_agency_to_runnable",
      "label": "Treasury-agency / runnable funding",
      "weight": 0.35,
      "contribution": 30.20029239766082
    },
    {
      "key": "hqla_narrow_lower_to_runnable",
      "label": "Narrow HQLA / runnable funding",
      "weight": 0.3,
      "contribution": 20.140350877192983
    }
  ],
  "composite_components": [
    {
      "key": "run_risk_index",
      "label": "Run Risk Index",
      "weight": 0.4,
      "score": 35.716312056737586,
      "contribution": 14.286524822695036
    },
    {
      "key": "alm_mismatch_index",
      "label": "ALM Mismatch Index",
      "weight": 0.4,
      "score": 51.498638426230755,
      "contribution": 20.599455370492304
    },
    {
      "key": "inverse_treasury_buffer_index",
      "label": "Inverse Treasury Buffer",
      "weight": 0.2,
      "score": 32.159356725146196,
      "contribution": 6.43187134502924
    }
  ],
  "supervised_outflow_score": 0.37917507637729425,
  "treasury_yield_date": "2024-12-31",
  "has_treasury_yield_history": 1,
  "yc_2yr": 4.25,
  "yc_10yr": 4.58,
  "yc_10y_3m_slope_bp": 20.999999999999996,
  "yc_10y_2y_slope_bp": 33.00000000000001,
  "yc_10yr_qoq_change_bp": 77.0,
  "has_ffiec_features": 1,
  "has_sod_features": 0,
  "index_version": "v1_ffiec_hybrid",
  "failed": false,
  "fail_date": null
}