{
  "cert": "31592",
  "name": "Security Federal Savings Bank",
  "peer_group": "community",
  "peer_group_bank_count": 4075,
  "assets": 34069,
  "deposits": 29874,
  "uninsured_pct": null,
  "state": "AL",
  "charter": "SB",
  "repdte": "2021-12-31",
  "run_risk_score": 48.22803645304814,
  "stickiness_score": 51.77196354695186,
  "run_risk": 48.36484414920797,
  "alm_mismatch": 38.74991791738381,
  "treasury_buffer": 40.25152641359172,
  "deposit_competition": 86.05007664793051,
  "deposit_competition_resilience": 13.94992335206949,
  "deposit_competition_score": 52.333883615352875,
  "funding_fragility": 46.79559954391837,
  "run_risk_components": [
    {
      "key": "uninsured_share",
      "label": "Uninsured deposits",
      "weight": 0.2,
      "percentile": 50.0,
      "contribution": 12.82051282051282
    },
    {
      "key": "brokered_share",
      "label": "Brokered deposits",
      "weight": 0.17,
      "percentile": 33.27821413807359,
      "contribution": 7.252944107016038
    },
    {
      "key": "list_service_share",
      "label": "List-service deposits",
      "weight": 0.08,
      "percentile": 38.95204630012402,
      "contribution": 3.995081671807591
    },
    {
      "key": "large_account_share",
      "label": "Large-account concentration",
      "weight": 0.1,
      "percentile": 50.0,
      "contribution": 6.41025641025641
    },
    {
      "key": "time_deposit_share",
      "label": "Time-deposit share",
      "weight": 0.05,
      "percentile": 94.89458453906573,
      "contribution": 6.08298618840165
    },
    {
      "key": "domestic_deposit_cost",
      "label": "Domestic deposit cost",
      "weight": 0.08,
      "percentile": 48.357098574085555,
      "contribution": 4.9597024178549285
    },
    {
      "key": "dep_growth_vol_4q",
      "label": "Deposit-growth volatility",
      "weight": 0.05,
      "percentile": 10.224695938981654,
      "contribution": 0.6554292268577983
    },
    {
      "key": "dep_drawdown_4q",
      "label": "Deposit drawdown",
      "weight": 0.05,
      "percentile": 94.39752832131822,
      "contribution": 6.051123610340911
    }
  ],
  "deposit_competition_components": [
    {
      "key": "outside_option_premium_pos_bp",
      "label": "Outside-option premium",
      "weight": 0.35,
      "percentile": 50.0,
      "contribution": 17.5
    },
    {
      "key": "pass_through_gap_bp",
      "label": "Pass-through gap",
      "weight": 0.2,
      "percentile": 50.0,
      "contribution": 10.0
    },
    {
      "key": "rate_sensitive_deposit_exposure",
      "label": "Rate-sensitive deposit exposure",
      "weight": 0.1,
      "percentile": 73.33883615352869,
      "contribution": 7.333883615352869
    },
    {
      "key": "premium_x_rate_sensitive_exposure",
      "label": "Premium \u00d7 rate-sensitive exposure",
      "weight": 0.2,
      "percentile": 50.0,
      "contribution": 10.0
    },
    {
      "key": "premium_x_dep_drawdown_4q",
      "label": "Premium \u00d7 deposit drawdown",
      "weight": 0.1,
      "percentile": 50.0,
      "contribution": 5.0
    },
    {
      "key": "premium_x_short_fhlb_share",
      "label": "Premium \u00d7 short FHLB share",
      "weight": 0.05,
      "percentile": 50.0,
      "contribution": 2.5
    }
  ],
  "alm_components": [
    {
      "key": "long_term_assets_to_stable_funding_baseline",
      "label": "Long-term assets / stable funding",
      "weight": 0.3,
      "contribution": 17.785166240409207
    },
    {
      "key": "volatile_to_liquid_lower",
      "label": "Volatile funding / liquid assets",
      "weight": 0.3,
      "contribution": 13.577759871071716
    },
    {
      "key": "security_vs_deposit_gap_baseline",
      "label": "Securities / deposit gap",
      "weight": 0.2,
      "contribution": 1.0379882289994649
    },
    {
      "key": "loans_to_core_deposits",
      "label": "Loans / core deposits",
      "weight": 0.1,
      "contribution": 1.3490035769034237
    },
    {
      "key": "short_fhlb_share",
      "label": "Short FHLB funding share",
      "weight": 0.1,
      "contribution": 5.0
    }
  ],
  "treasury_buffer_components": [
    {
      "key": "treasury_to_uninsured_after_100bp",
      "label": "Treasuries / uninsured after 100 bp shock",
      "weight": 0.35,
      "contribution": 17.5
    },
    {
      "key": "treasury_agency_to_runnable",
      "label": "Treasury-agency / runnable funding",
      "weight": 0.35,
      "contribution": 5.063711176002124
    },
    {
      "key": "hqla_narrow_lower_to_runnable",
      "label": "Narrow HQLA / runnable funding",
      "weight": 0.3,
      "contribution": 17.687815237589593
    }
  ],
  "composite_components": [
    {
      "key": "run_risk_index",
      "label": "Run Risk Index",
      "weight": 0.4,
      "score": 48.36484414920797,
      "contribution": 19.345937659683187
    },
    {
      "key": "alm_mismatch_index",
      "label": "ALM Mismatch Index",
      "weight": 0.4,
      "score": 38.74991791738381,
      "contribution": 15.499967166953525
    },
    {
      "key": "inverse_treasury_buffer_index",
      "label": "Inverse Treasury Buffer",
      "weight": 0.2,
      "score": 59.74847358640828,
      "contribution": 11.949694717281657
    }
  ],
  "supervised_outflow_score": 0.41135098154399596,
  "treasury_yield_date": null,
  "has_treasury_yield_history": 0,
  "yc_2yr": null,
  "yc_10yr": null,
  "yc_10y_3m_slope_bp": null,
  "yc_10y_2y_slope_bp": null,
  "yc_10yr_qoq_change_bp": null,
  "has_ffiec_features": 1,
  "has_sod_features": 1,
  "index_version": "v1_ffiec_hybrid",
  "failed": false,
  "fail_date": null
}