{
  "cert": "34011",
  "name": "Village Bank and Trust, National Association",
  "peer_group": "regional",
  "peer_group_bank_count": 976,
  "assets": 3100228,
  "deposits": 2572549,
  "uninsured_pct": 0.41026662660264196,
  "state": "IL",
  "charter": "N",
  "repdte": "2024-12-31",
  "run_risk_score": 68.95827018929542,
  "stickiness_score": 31.04172981070458,
  "run_risk": 93.44827586206897,
  "alm_mismatch": 45.14790723000356,
  "treasury_buffer": 29.12225864862018,
  "deposit_competition": 30.804597701149426,
  "deposit_competition_resilience": 69.19540229885058,
  "deposit_competition_score": 48.81263534572914,
  "funding_fragility": 69.61402150710498,
  "run_risk_components": [
    {
      "key": "uninsured_share",
      "label": "Uninsured deposits",
      "weight": 0.2,
      "percentile": 75.83756345177665,
      "contribution": 19.44552909019914
    },
    {
      "key": "brokered_share",
      "label": "Brokered deposits",
      "weight": 0.17,
      "percentile": 86.08695652173914,
      "contribution": 18.76254180602007
    },
    {
      "key": "list_service_share",
      "label": "List-service deposits",
      "weight": 0.08,
      "percentile": 84.68227424749163,
      "contribution": 8.685361461281193
    },
    {
      "key": "large_account_share",
      "label": "Large-account concentration",
      "weight": 0.1,
      "percentile": 50.0,
      "contribution": 6.41025641025641
    },
    {
      "key": "time_deposit_share",
      "label": "Time-deposit share",
      "weight": 0.05,
      "percentile": 22.34113712374582,
      "contribution": 1.4321241745990911
    },
    {
      "key": "domestic_deposit_cost",
      "label": "Domestic deposit cost",
      "weight": 0.08,
      "percentile": 76.03748326639894,
      "contribution": 7.798716232451174
    },
    {
      "key": "dep_growth_vol_4q",
      "label": "Deposit-growth volatility",
      "weight": 0.05,
      "percentile": 74.15480427046263,
      "contribution": 4.753513094260425
    },
    {
      "key": "dep_drawdown_4q",
      "label": "Deposit drawdown",
      "weight": 0.05,
      "percentile": 26.055555555555554,
      "contribution": 1.6702279202279202
    }
  ],
  "deposit_competition_components": [
    {
      "key": "outside_option_premium_pos_bp",
      "label": "Outside-option premium",
      "weight": 0.35,
      "percentile": 23.98482820169567,
      "contribution": 8.394689870593485
    },
    {
      "key": "pass_through_gap_bp",
      "label": "Pass-through gap",
      "weight": 0.2,
      "percentile": 48.46016514170944,
      "contribution": 9.69203302834189
    },
    {
      "key": "rate_sensitive_deposit_exposure",
      "label": "Rate-sensitive deposit exposure",
      "weight": 0.1,
      "percentile": 94.27999109726241,
      "contribution": 9.427999109726242
    },
    {
      "key": "premium_x_rate_sensitive_exposure",
      "label": "Premium \u00d7 rate-sensitive exposure",
      "weight": 0.2,
      "percentile": 90.87460954930835,
      "contribution": 18.17492190986167
    },
    {
      "key": "premium_x_dep_drawdown_4q",
      "label": "Premium \u00d7 deposit drawdown",
      "weight": 0.1,
      "percentile": 26.17135207496653,
      "contribution": 2.6171352074966534
    },
    {
      "key": "premium_x_short_fhlb_share",
      "label": "Premium \u00d7 short FHLB share",
      "weight": 0.05,
      "percentile": 10.117124394184168,
      "contribution": 0.5058562197092085
    }
  ],
  "alm_components": [
    {
      "key": "long_term_assets_to_stable_funding_baseline",
      "label": "Long-term assets / stable funding",
      "weight": 0.3,
      "contribution": 8.933951332560834
    },
    {
      "key": "volatile_to_liquid_lower",
      "label": "Volatile funding / liquid assets",
      "weight": 0.3,
      "contribution": 24.96031746031746
    },
    {
      "key": "security_vs_deposit_gap_baseline",
      "label": "Securities / deposit gap",
      "weight": 0.2,
      "contribution": 2.826855123674912
    },
    {
      "key": "loans_to_core_deposits",
      "label": "Loans / core deposits",
      "weight": 0.1,
      "contribution": 7.471264367816092
    },
    {
      "key": "short_fhlb_share",
      "label": "Short FHLB funding share",
      "weight": 0.1,
      "contribution": 0.955518945634267
    }
  ],
  "treasury_buffer_components": [
    {
      "key": "treasury_to_uninsured_after_100bp",
      "label": "Treasuries / uninsured after 100 bp shock",
      "weight": 0.35,
      "contribution": 7.245085995085995
    },
    {
      "key": "treasury_agency_to_runnable",
      "label": "Treasury-agency / runnable funding",
      "weight": 0.35,
      "contribution": 13.464658169177287
    },
    {
      "key": "hqla_narrow_lower_to_runnable",
      "label": "Narrow HQLA / runnable funding",
      "weight": 0.3,
      "contribution": 8.412514484356894
    }
  ],
  "composite_components": [
    {
      "key": "run_risk_index",
      "label": "Run Risk Index",
      "weight": 0.4,
      "score": 93.44827586206897,
      "contribution": 37.37931034482759
    },
    {
      "key": "alm_mismatch_index",
      "label": "ALM Mismatch Index",
      "weight": 0.4,
      "score": 45.14790723000356,
      "contribution": 18.059162892001424
    },
    {
      "key": "inverse_treasury_buffer_index",
      "label": "Inverse Treasury Buffer",
      "weight": 0.2,
      "score": 70.87774135137983,
      "contribution": 14.175548270275966
    }
  ],
  "supervised_outflow_score": 0.47309506988921934,
  "treasury_yield_date": "2024-12-31",
  "has_treasury_yield_history": 1,
  "yc_2yr": 4.25,
  "yc_10yr": 4.58,
  "yc_10y_3m_slope_bp": 20.999999999999996,
  "yc_10y_2y_slope_bp": 33.00000000000001,
  "yc_10yr_qoq_change_bp": 77.0,
  "has_ffiec_features": 1,
  "has_sod_features": 0,
  "index_version": "v1_ffiec_hybrid",
  "failed": false,
  "fail_date": null
}