{
  "cert": "4028",
  "name": "First Dakota National Bank",
  "peer_group": "regional",
  "peer_group_bank_count": 976,
  "assets": 2916496,
  "deposits": 2633781,
  "uninsured_pct": 0.32802233746845316,
  "state": "SD",
  "charter": "N",
  "repdte": "2024-12-31",
  "run_risk_score": 50.954698174958565,
  "stickiness_score": 49.045301825041435,
  "run_risk": 44.712643678160916,
  "alm_mismatch": 49.96877888566646,
  "treasury_buffer": 25.477994453950426,
  "deposit_competition": 41.03448275862069,
  "deposit_competition_resilience": 58.96551724137931,
  "deposit_competition_score": 51.70256569986931,
  "funding_fragility": 52.776970134740864,
  "run_risk_components": [
    {
      "key": "uninsured_share",
      "label": "Uninsured deposits",
      "weight": 0.2,
      "percentile": 54.51776649746193,
      "contribution": 13.978914486528701
    },
    {
      "key": "brokered_share",
      "label": "Brokered deposits",
      "weight": 0.17,
      "percentile": 61.2263099219621,
      "contribution": 13.34419575222251
    },
    {
      "key": "list_service_share",
      "label": "List-service deposits",
      "weight": 0.08,
      "percentile": 39.40914158305463,
      "contribution": 4.0419632392876546
    },
    {
      "key": "large_account_share",
      "label": "Large-account concentration",
      "weight": 0.1,
      "percentile": 50.0,
      "contribution": 6.41025641025641
    },
    {
      "key": "time_deposit_share",
      "label": "Time-deposit share",
      "weight": 0.05,
      "percentile": 22.653288740245262,
      "contribution": 1.4521338936054655
    },
    {
      "key": "domestic_deposit_cost",
      "label": "Domestic deposit cost",
      "weight": 0.08,
      "percentile": 75.83668005354752,
      "contribution": 7.778121031133079
    },
    {
      "key": "dep_growth_vol_4q",
      "label": "Deposit-growth volatility",
      "weight": 0.05,
      "percentile": 6.93950177935943,
      "contribution": 0.4448398576512455
    },
    {
      "key": "dep_drawdown_4q",
      "label": "Deposit drawdown",
      "weight": 0.05,
      "percentile": 54.666666666666664,
      "contribution": 3.5042735042735043
    }
  ],
  "deposit_competition_components": [
    {
      "key": "outside_option_premium_pos_bp",
      "label": "Outside-option premium",
      "weight": 0.35,
      "percentile": 24.185631414547075,
      "contribution": 8.464970995091475
    },
    {
      "key": "pass_through_gap_bp",
      "label": "Pass-through gap",
      "weight": 0.2,
      "percentile": 48.46016514170944,
      "contribution": 9.69203302834189
    },
    {
      "key": "rate_sensitive_deposit_exposure",
      "label": "Rate-sensitive deposit exposure",
      "weight": 0.1,
      "percentile": 85.26596928555531,
      "contribution": 8.526596928555533
    },
    {
      "key": "premium_x_rate_sensitive_exposure",
      "label": "Premium \u00d7 rate-sensitive exposure",
      "weight": 0.2,
      "percentile": 85.18518518518519,
      "contribution": 17.037037037037038
    },
    {
      "key": "premium_x_dep_drawdown_4q",
      "label": "Premium \u00d7 deposit drawdown",
      "weight": 0.1,
      "percentile": 54.81927710843374,
      "contribution": 5.481927710843374
    },
    {
      "key": "premium_x_short_fhlb_share",
      "label": "Premium \u00d7 short FHLB share",
      "weight": 0.05,
      "percentile": 50.0,
      "contribution": 2.5
    }
  ],
  "alm_components": [
    {
      "key": "long_term_assets_to_stable_funding_baseline",
      "label": "Long-term assets / stable funding",
      "weight": 0.3,
      "contribution": 7.508690614136732
    },
    {
      "key": "volatile_to_liquid_lower",
      "label": "Volatile funding / liquid assets",
      "weight": 0.3,
      "contribution": 29.72222222222222
    },
    {
      "key": "security_vs_deposit_gap_baseline",
      "label": "Securities / deposit gap",
      "weight": 0.2,
      "contribution": 2.473498233215548
    },
    {
      "key": "loans_to_core_deposits",
      "label": "Loans / core deposits",
      "weight": 0.1,
      "contribution": 5.264367816091954
    },
    {
      "key": "short_fhlb_share",
      "label": "Short FHLB funding share",
      "weight": 0.1,
      "contribution": 5.0
    }
  ],
  "treasury_buffer_components": [
    {
      "key": "treasury_to_uninsured_after_100bp",
      "label": "Treasuries / uninsured after 100 bp shock",
      "weight": 0.35,
      "contribution": 7.245085995085995
    },
    {
      "key": "treasury_agency_to_runnable",
      "label": "Treasury-agency / runnable funding",
      "weight": 0.35,
      "contribution": 13.991888760139052
    },
    {
      "key": "hqla_narrow_lower_to_runnable",
      "label": "Narrow HQLA / runnable funding",
      "weight": 0.3,
      "contribution": 4.241019698725377
    }
  ],
  "composite_components": [
    {
      "key": "run_risk_index",
      "label": "Run Risk Index",
      "weight": 0.4,
      "score": 44.712643678160916,
      "contribution": 17.885057471264368
    },
    {
      "key": "alm_mismatch_index",
      "label": "ALM Mismatch Index",
      "weight": 0.4,
      "score": 49.96877888566646,
      "contribution": 19.987511554266586
    },
    {
      "key": "inverse_treasury_buffer_index",
      "label": "Inverse Treasury Buffer",
      "weight": 0.2,
      "score": 74.52200554604957,
      "contribution": 14.904401109209914
    }
  ],
  "supervised_outflow_score": 0.15871957475378493,
  "treasury_yield_date": "2024-12-31",
  "has_treasury_yield_history": 1,
  "yc_2yr": 4.25,
  "yc_10yr": 4.58,
  "yc_10y_3m_slope_bp": 20.999999999999996,
  "yc_10y_2y_slope_bp": 33.00000000000001,
  "yc_10yr_qoq_change_bp": 77.0,
  "has_ffiec_features": 1,
  "has_sod_features": 0,
  "index_version": "v1_ffiec_hybrid",
  "failed": false,
  "fail_date": null
}