{
  "cert": "8904",
  "name": "The Nodaway Valley Bank",
  "peer_group": "regional",
  "peer_group_bank_count": 976,
  "assets": 1422024,
  "deposits": 1226544,
  "uninsured_pct": 0.18558893932871548,
  "state": "MO",
  "charter": "NM",
  "repdte": "2024-12-31",
  "run_risk_score": 27.796853394811176,
  "stickiness_score": 72.20314660518882,
  "run_risk": 1.3793103448275863,
  "alm_mismatch": 44.22157558557309,
  "treasury_buffer": 81.32772797025405,
  "deposit_competition": 93.33333333333333,
  "deposit_competition_resilience": 6.666666666666671,
  "deposit_competition_score": 75.1422506022491,
  "funding_fragility": 21.974808778109463,
  "run_risk_components": [
    {
      "key": "uninsured_share",
      "label": "Uninsured deposits",
      "weight": 0.2,
      "percentile": 14.923857868020304,
      "contribution": 3.826630222569309
    },
    {
      "key": "brokered_share",
      "label": "Brokered deposits",
      "weight": 0.17,
      "percentile": 25.908584169453736,
      "contribution": 5.646742703598892
    },
    {
      "key": "list_service_share",
      "label": "List-service deposits",
      "weight": 0.08,
      "percentile": 39.40914158305463,
      "contribution": 4.0419632392876546
    },
    {
      "key": "large_account_share",
      "label": "Large-account concentration",
      "weight": 0.1,
      "percentile": 50.0,
      "contribution": 6.41025641025641
    },
    {
      "key": "time_deposit_share",
      "label": "Time-deposit share",
      "weight": 0.05,
      "percentile": 28.383500557413598,
      "contribution": 1.8194551639367693
    },
    {
      "key": "domestic_deposit_cost",
      "label": "Domestic deposit cost",
      "weight": 0.08,
      "percentile": 14.2347166443552,
      "contribution": 1.4599709378825845
    },
    {
      "key": "dep_growth_vol_4q",
      "label": "Deposit-growth volatility",
      "weight": 0.05,
      "percentile": 11.699288256227758,
      "contribution": 0.7499543753992152
    },
    {
      "key": "dep_drawdown_4q",
      "label": "Deposit drawdown",
      "weight": 0.05,
      "percentile": 59.93333333333334,
      "contribution": 3.841880341880342
    }
  ],
  "deposit_competition_components": [
    {
      "key": "outside_option_premium_pos_bp",
      "label": "Outside-option premium",
      "weight": 0.35,
      "percentile": 85.7875948237394,
      "contribution": 30.025658188308785
    },
    {
      "key": "pass_through_gap_bp",
      "label": "Pass-through gap",
      "weight": 0.2,
      "percentile": 48.46016514170944,
      "contribution": 9.69203302834189
    },
    {
      "key": "rate_sensitive_deposit_exposure",
      "label": "Rate-sensitive deposit exposure",
      "weight": 0.1,
      "percentile": 69.46361006009349,
      "contribution": 6.946361006009349
    },
    {
      "key": "premium_x_rate_sensitive_exposure",
      "label": "Premium \u00d7 rate-sensitive exposure",
      "weight": 0.2,
      "percentile": 86.36769299419902,
      "contribution": 17.273538598839803
    },
    {
      "key": "premium_x_dep_drawdown_4q",
      "label": "Premium \u00d7 deposit drawdown",
      "weight": 0.1,
      "percentile": 63.52074966532798,
      "contribution": 6.352074966532799
    },
    {
      "key": "premium_x_short_fhlb_share",
      "label": "Premium \u00d7 short FHLB share",
      "weight": 0.05,
      "percentile": 97.05169628432955,
      "contribution": 4.852584814216478
    }
  ],
  "alm_components": [
    {
      "key": "long_term_assets_to_stable_funding_baseline",
      "label": "Long-term assets / stable funding",
      "weight": 0.3,
      "contribution": 12.132097334878333
    },
    {
      "key": "volatile_to_liquid_lower",
      "label": "Volatile funding / liquid assets",
      "weight": 0.3,
      "contribution": 5.238095238095237
    },
    {
      "key": "security_vs_deposit_gap_baseline",
      "label": "Securities / deposit gap",
      "weight": 0.2,
      "contribution": 15.571260306242639
    },
    {
      "key": "loans_to_core_deposits",
      "label": "Loans / core deposits",
      "weight": 0.1,
      "contribution": 2.4827586206896552
    },
    {
      "key": "short_fhlb_share",
      "label": "Short FHLB funding share",
      "weight": 0.1,
      "contribution": 8.797364085667216
    }
  ],
  "treasury_buffer_components": [
    {
      "key": "treasury_to_uninsured_after_100bp",
      "label": "Treasuries / uninsured after 100 bp shock",
      "weight": 0.35,
      "contribution": 22.05773955773956
    },
    {
      "key": "treasury_agency_to_runnable",
      "label": "Treasury-agency / runnable funding",
      "weight": 0.35,
      "contribution": 33.58053302433372
    },
    {
      "key": "hqla_narrow_lower_to_runnable",
      "label": "Narrow HQLA / runnable funding",
      "weight": 0.3,
      "contribution": 25.689455388180765
    }
  ],
  "composite_components": [
    {
      "key": "run_risk_index",
      "label": "Run Risk Index",
      "weight": 0.4,
      "score": 1.3793103448275863,
      "contribution": 0.5517241379310346
    },
    {
      "key": "alm_mismatch_index",
      "label": "ALM Mismatch Index",
      "weight": 0.4,
      "score": 44.22157558557309,
      "contribution": 17.688630234229237
    },
    {
      "key": "inverse_treasury_buffer_index",
      "label": "Inverse Treasury Buffer",
      "weight": 0.2,
      "score": 18.672272029745955,
      "contribution": 3.734454405949191
    }
  ],
  "supervised_outflow_score": 0.137401315079538,
  "treasury_yield_date": "2024-12-31",
  "has_treasury_yield_history": 1,
  "yc_2yr": 4.25,
  "yc_10yr": 4.58,
  "yc_10y_3m_slope_bp": 20.999999999999996,
  "yc_10y_2y_slope_bp": 33.00000000000001,
  "yc_10yr_qoq_change_bp": 77.0,
  "has_ffiec_features": 1,
  "has_sod_features": 0,
  "index_version": "v1_ffiec_hybrid",
  "failed": false,
  "fail_date": null
}